pynostr_cli/__init__.py
pynostr_cli/cli.py
pynostr_cli/key.py
pynostr_cli-0.1.2.dist-info/METADATA
pynostr_cli-0.1.2.dist-info/WHEEL
pynostr_cli-0.1.2.dist-info/entry_points.txt
pynostr_cli-0.1.2.dist-info/RECORD
